diplib/PyDIPjavaio.cpython-311-darwin.so
diplib/viewer.py
diplib/dipview.py
diplib/loadjvm.py
diplib/libDIPviewer.dylib
diplib/__init__.py
diplib/libDIP.dylib
diplib/documentation_urls.py
diplib/DIPjavaio.jar
diplib/javaio.py
diplib/PyDIP_bin.cpython-311-darwin.so
diplib/PyDIPviewer.cpython-311-darwin.so
diplib/PyDIP_py.py
diplib/libDIPjavaio.dylib
diplib/__main__.py
diplib/.dylibs/libomp.dylib
diplib/.dylibs/libglfw.3.4.dylib
diplib-3.6.0.dist-info/RECORD
diplib-3.6.0.dist-info/WHEEL
diplib-3.6.0.dist-info/entry_points.txt
diplib-3.6.0.dist-info/top_level.txt
diplib-3.6.0.dist-info/METADATA
diplib-3.6.0.dist-info/licenses/README.md
diplib-3.6.0.dist-info/licenses/LICENSE.txt
